[
    {
        "kind": "Listing", 
        "data": {
            "modhash": "", 
            "children": [
                {
                    "kind": "t3", 
                    "data": {
                        "contest_mode": false, 
                        "subreddit_name_prefixed": "r/RoastMe", 
                        "banned_by": null, 
                        "media_embed": {}, 
                        "thumbnail_width": 140, 
                        "subreddit": "RoastMe", 
                        "selftext_html": null, 
                        "selftext": "", 
                        "likes": null, 
                        "suggested_sort": null, 
                        "user_reports": [], 
                        "secure_media": null, 
                        "link_flair_text": null, 
                        "id": "3tdp4h", 
                        "view_count": null, 
                        "secure_media_embed": {}, 
                        "clicked": false, 
                        "report_reasons": null, 
                        "author": "taybuchanan", 
                        "saved": false, 
                        "mod_reports": [], 
                        "name": "t3_3tdp4h", 
                        "score": 1, 
                        "approved_by": null, 
                        "over_18": false, 
                        "domain": "imgur.com", 
                        "hidden": false, 
                        "preview": {
                            "images": [
                                {
                                    "source": {
                                        "url": "https://i.redditmedia.com/v-7LJ8LFJjcaVuNJAIdvvXeMlkiL1iN8i88XXUoZJCo.jpg?s=a899afb334868a5f279ddd400f794f33", 
                                        "width": 480, 
                                        "height": 270
                                    }, 
                                    "resolutions": [
                                        {
                                            "url": "https://i.redditmedia.com/v-7LJ8LFJjcaVuNJAIdvvXeMlkiL1iN8i88XXUoZJCo.jpg?fit=crop&amp;crop=faces%2Centropy&amp;arh=2&amp;w=108&amp;s=62f0d9022ef95b98de1d71e221f89892", 
                                            "width": 108, 
                                            "height": 60
                                        }, 
                                        {
                                            "url": "https://i.redditmedia.com/v-7LJ8LFJjcaVuNJAIdvvXeMlkiL1iN8i88XXUoZJCo.jpg?fit=crop&amp;crop=faces%2Centropy&amp;arh=2&amp;w=216&amp;s=6c3e89529f6acd3c027ed6a74c98f48b", 
                                            "width": 216, 
                                            "height": 121
                                        }, 
                                        {
                                            "url": "https://i.redditmedia.com/v-7LJ8LFJjcaVuNJAIdvvXeMlkiL1iN8i88XXUoZJCo.jpg?fit=crop&amp;crop=faces%2Centropy&amp;arh=2&amp;w=320&amp;s=4df93e40397516bf7aca305774e8765e", 
                                            "width": 320, 
                                            "height": 180
                                        }
                                    ], 
                                    "variants": {}, 
                                    "id": "vdeHn-YPwGbrbWL6DruX3EIWz7eMYql_mFU7s0_bGm4"
                                }
                            ], 
                            "enabled": false
                        }, 
                        "thumbnail": "https://b.thumbs.redditmedia.com/MJ7aLyCuySXghA12xLeE8mrLQkLlkIDr2y5VQbDdPaI.jpg", 
                        "subreddit_id": "t5_37xo2", 
                        "edited": false, 
                        "link_flair_css_class": null, 
                        "author_flair_css_class": "roastlink", 
                        "gilded": 0, 
                        "downs": 0, 
                        "brand_safe": true, 
                        "archived": true, 
                        "removal_reason": null, 
                        "post_hint": "link", 
                        "can_gild": false, 
                        "thumbnail_height": 78, 
                        "hide_score": false, 
                        "spoiler": false, 
                        "permalink": "/r/RoastMe/comments/3tdp4h/roast_me/", 
                        "num_reports": null, 
                        "locked": false, 
                        "stickied": false, 
                        "created": 1447929444.0, 
                        "url": "http://imgur.com/gallery/ctDrx8g", 
                        "author_flair_text": "http://redd.it/3tii0k", 
                        "quarantine": false, 
                        "title": "Roast Me", 
                        "created_utc": 1447900644.0, 
                        "distinguished": null, 
                        "media": null, 
                        "upvote_ratio": 0.67, 
                        "num_comments": 6, 
                        "is_self": false, 
                        "visited": false, 
                        "subreddit_type": "public", 
                        "is_video": false, 
                        "ups": 1
                    }
                }
            ], 
            "after": null, 
            "before": null
        }
    }, 
    {
        "kind": "Listing", 
        "data": {
            "modhash": "", 
            "children": [
                {
                    "kind": "t1", 
                    "data": {
                        "subreddit_id": "t5_37xo2", 
                        "banned_by": null, 
                        "removal_reason": null, 
                        "link_id": "t3_3tdp4h", 
                        "likes": null, 
                        "replies": "", 
                        "user_reports": [], 
                        "saved": false, 
                        "id": "cx5atrf", 
                        "gilded": 0, 
                        "archived": true, 
                        "score": 3, 
                        "report_reasons": null, 
                        "author": "sandyravage_", 
                        "parent_id": "t3_3tdp4h", 
                        "subreddit_name_prefixed": "r/RoastMe", 
                        "approved_by": null, 
                        "controversiality": 0, 
                        "body": "Giggity giggity giggity.", 
                        "edited": false, 
                        "author_flair_css_class": null, 
                        "downs": 0, 
                        "body_html": "&lt;div class=\"md\"&gt;&lt;p&gt;Giggity giggity giggity.&lt;/p&gt;\n&lt;/div&gt;", 
                        "can_gild": true, 
                        "subreddit": "RoastMe", 
                        "name": "t1_cx5atrf", 
                        "score_hidden": false, 
                        "num_reports": null, 
                        "stickied": false, 
                        "created": 1447930504.0, 
                        "author_flair_text": null, 
                        "created_utc": 1447901704.0, 
                        "distinguished": null, 
                        "depth": 0, 
                        "mod_reports": [], 
                        "subreddit_type": "public", 
                        "ups": 3
                    }
                }, 
                {
                    "kind": "t1", 
                    "data": {
                        "subreddit_id": "t5_37xo2", 
                        "banned_by": null, 
                        "removal_reason": null, 
                        "link_id": "t3_3tdp4h", 
                        "likes": null, 
                        "replies": "", 
                        "user_reports": [], 
                        "saved": false, 
                        "id": "cx5arvv", 
                        "gilded": 0, 
                        "archived": true, 
                        "score": 1, 
                        "report_reasons": null, 
                        "author": "[deleted]", 
                        "parent_id": "t3_3tdp4h", 
                        "subreddit_name_prefixed": "r/RoastMe", 
                        "approved_by": null, 
                        "controversiality": 0, 
                        "body": "The kind of man parents warn their children to be careful around.", 
                        "edited": false, 
                        "author_flair_css_class": null, 
                        "downs": 0, 
                        "body_html": "&lt;div class=\"md\"&gt;&lt;p&gt;The kind of man parents warn their children to be careful around.&lt;/p&gt;\n&lt;/div&gt;", 
                        "can_gild": false, 
                        "subreddit": "RoastMe", 
                        "name": "t1_cx5arvv", 
                        "score_hidden": false, 
                        "num_reports": null, 
                        "stickied": false, 
                        "created": 1447930407.0, 
                        "author_flair_text": null, 
                        "created_utc": 1447901607.0, 
                        "distinguished": null, 
                        "depth": 0, 
                        "mod_reports": [], 
                        "subreddit_type": "public", 
                        "ups": 1
                    }
                }, 
                {
                    "kind": "t1", 
                    "data": {
                        "subreddit_id": "t5_37xo2", 
                        "banned_by": null, 
                        "removal_reason": null, 
                        "link_id": "t3_3tdp4h", 
                        "likes": null, 
                        "replies": "", 
                        "user_reports": [], 
                        "saved": false, 
                        "id": "cx5bci5", 
                        "gilded": 0, 
                        "archived": true, 
                        "score": 1, 
                        "report_reasons": null, 
                        "author": "written_emotions", 
                        "parent_id": "t3_3tdp4h", 
                        "subreddit_name_prefixed": "r/RoastMe", 
                        "approved_by": null, 
                        "controversiality": 0, 
                        "body": "You kind of look like Humpty Dumpty, if Humpty Dumpty had a huge lumpy dump in the toilet.", 
                        "edited": false, 
                        "author_flair_css_class": null, 
                        "downs": 0, 
                        "body_html": "&lt;div class=\"md\"&gt;&lt;p&gt;You kind of look like Humpty Dumpty, if Humpty Dumpty had a huge lumpy dump in the toilet.&lt;/p&gt;\n&lt;/div&gt;", 
                        "can_gild": true, 
                        "subreddit": "RoastMe", 
                        "name": "t1_cx5bci5", 
                        "score_hidden": false, 
                        "num_reports": null, 
                        "stickied": false, 
                        "created": 1447931436.0, 
                        "author_flair_text": null, 
                        "created_utc": 1447902636.0, 
                        "distinguished": null, 
                        "depth": 0, 
                        "mod_reports": [], 
                        "subreddit_type": "public", 
                        "ups": 1
                    }
                }, 
                {
                    "kind": "t1", 
                    "data": {
                        "subreddit_id": "t5_37xo2", 
                        "banned_by": null, 
                        "removal_reason": null, 
                        "link_id": "t3_3tdp4h", 
                        "likes": null, 
                        "replies": "", 
                        "user_reports": [], 
                        "saved": false, 
                        "id": "cx5bm9p", 
                        "gilded": 0, 
                        "archived": true, 
                        "score": 1, 
                        "report_reasons": null, 
                        "author": "motherboy", 
                        "parent_id": "t3_3tdp4h", 
                        "subreddit_name_prefixed": "r/RoastMe", 
                        "approved_by": null, 
                        "controversiality": 0, 
                        "body": "Your egg-shaped head looks really bad with that haircut.", 
                        "edited": false, 
                        "author_flair_css_class": null, 
                        "downs": 0, 
                        "body_html": "&lt;div class=\"md\"&gt;&lt;p&gt;Your egg-shaped head looks really bad with that haircut.&lt;/p&gt;\n&lt;/div&gt;", 
                        "can_gild": true, 
                        "subreddit": "RoastMe", 
                        "name": "t1_cx5bm9p", 
                        "score_hidden": false, 
                        "num_reports": null, 
                        "stickied": false, 
                        "created": 1447931926.0, 
                        "author_flair_text": null, 
                        "created_utc": 1447903126.0, 
                        "distinguished": null, 
                        "depth": 0, 
                        "mod_reports": [], 
                        "subreddit_type": "public", 
                        "ups": 1
                    }
                }, 
                {
                    "kind": "t1", 
                    "data": {
                        "subreddit_id": "t5_37xo2", 
                        "banned_by": null, 
                        "removal_reason": null, 
                        "link_id": "t3_3tdp4h", 
                        "likes": null, 
                        "replies": "", 
                        "user_reports": [], 
                        "saved": false, 
                        "id": "cx5by9g", 
                        "gilded": 0, 
                        "archived": true, 
                        "score": 1, 
                        "report_reasons": null, 
                        "author": "congenialprick", 
                        "parent_id": "t3_3tdp4h", 
                        "subreddit_name_prefixed": "r/RoastMe", 
                        "approved_by": null, 
                        "controversiality": 0, 
                        "body": "So, if Jonah Hill was a Proactiv spokesperson, this would be the \"before\" picture they show. ", 
                        "edited": false, 
                        "author_flair_css_class": null, 
                        "downs": 0, 
                        "body_html": "&lt;div class=\"md\"&gt;&lt;p&gt;So, if Jonah Hill was a Proactiv spokesperson, this would be the &amp;quot;before&amp;quot; picture they show. &lt;/p&gt;\n&lt;/div&gt;", 
                        "can_gild": true, 
                        "subreddit": "RoastMe", 
                        "name": "t1_cx5by9g", 
                        "score_hidden": false, 
                        "num_reports": null, 
                        "stickied": false, 
                        "created": 1447932540.0, 
                        "author_flair_text": null, 
                        "created_utc": 1447903740.0, 
                        "distinguished": null, 
                        "depth": 0, 
                        "mod_reports": [], 
                        "subreddit_type": "public", 
                        "ups": 1
                    }
                }, 
                {
                    "kind": "t1", 
                    "data": {
                        "subreddit_id": "t5_37xo2", 
                        "banned_by": null, 
                        "removal_reason": null, 
                        "link_id": "t3_3tdp4h", 
                        "likes": null, 
                        "replies": "", 
                        "user_reports": [], 
                        "saved": false, 
                        "id": "cx5fxhi", 
                        "gilded": 0, 
                        "archived": true, 
                        "score": 1, 
                        "report_reasons": null, 
                        "author": "id_profiler", 
                        "parent_id": "t3_3tdp4h", 
                        "subreddit_name_prefixed": "r/RoastMe", 
                        "approved_by": null, 
                        "controversiality": 0, 
                        "body": "Wow your head is the exact same shape as an egg", 
                        "edited": false, 
                        "author_flair_css_class": null, 
                        "downs": 0, 
                        "body_html": "&lt;div class=\"md\"&gt;&lt;p&gt;Wow your head is the exact same shape as an egg&lt;/p&gt;\n&lt;/div&gt;", 
                        "can_gild": true, 
                        "subreddit": "RoastMe", 
                        "name": "t1_cx5fxhi", 
                        "score_hidden": false, 
                        "num_reports": null, 
                        "stickied": false, 
                        "created": 1447940748.0, 
                        "author_flair_text": null, 
                        "created_utc": 1447911948.0, 
                        "distinguished": null, 
                        "depth": 0, 
                        "mod_reports": [], 
                        "subreddit_type": "public", 
                        "ups": 1
                    }
                }
            ], 
            "after": null, 
            "before": null
        }
    }
]