[
    {
        "kind": "Listing", 
        "data": {
            "modhash": "", 
            "children": [
                {
                    "kind": "t3", 
                    "data": {
                        "contest_mode": false, 
                        "subreddit_name_prefixed": "r/RoastMe", 
                        "banned_by": null, 
                        "media_embed": {}, 
                        "thumbnail_width": 140, 
                        "subreddit": "RoastMe", 
                        "selftext_html": null, 
                        "selftext": "", 
                        "likes": null, 
                        "suggested_sort": null, 
                        "user_reports": [], 
                        "secure_media": null, 
                        "link_flair_text": null, 
                        "id": "3t90m4", 
                        "view_count": null, 
                        "secure_media_embed": {}, 
                        "clicked": false, 
                        "report_reasons": null, 
                        "author": "kitcatchik94", 
                        "saved": false, 
                        "mod_reports": [], 
                        "name": "t3_3t90m4", 
                        "score": 3, 
                        "approved_by": null, 
                        "over_18": false, 
                        "domain": "imgur.com", 
                        "hidden": false, 
                        "preview": {
                            "images": [
                                {
                                    "source": {
                                        "url": "https://i.redditmedia.com/GwDNkDHfaO-SzepHuzgWLWi-4Qh3ufzt4YI3mi0Rwkw.jpg?s=8cd72675134d6a260ce5f8bbd6218192", 
                                        "width": 2988, 
                                        "height": 5312
                                    }, 
                                    "resolutions": [
                                        {
                                            "url": "https://i.redditmedia.com/GwDNkDHfaO-SzepHuzgWLWi-4Qh3ufzt4YI3mi0Rwkw.jpg?fit=crop&amp;crop=faces%2Centropy&amp;arh=2&amp;w=108&amp;s=48a4fe6d7f6bf0c25e627d53c9d51d32", 
                                            "width": 108, 
                                            "height": 192
                                        }, 
                                        {
                                            "url": "https://i.redditmedia.com/GwDNkDHfaO-SzepHuzgWLWi-4Qh3ufzt4YI3mi0Rwkw.jpg?fit=crop&amp;crop=faces%2Centropy&amp;arh=2&amp;w=216&amp;s=58787ef7b895552849bf67b575f05c14", 
                                            "width": 216, 
                                            "height": 384
                                        }, 
                                        {
                                            "url": "https://i.redditmedia.com/GwDNkDHfaO-SzepHuzgWLWi-4Qh3ufzt4YI3mi0Rwkw.jpg?fit=crop&amp;crop=faces%2Centropy&amp;arh=2&amp;w=320&amp;s=d3ae628f59652cbb6e702d227b6e10d6", 
                                            "width": 320, 
                                            "height": 568
                                        }, 
                                        {
                                            "url": "https://i.redditmedia.com/GwDNkDHfaO-SzepHuzgWLWi-4Qh3ufzt4YI3mi0Rwkw.jpg?fit=crop&amp;crop=faces%2Centropy&amp;arh=2&amp;w=640&amp;s=b1948c49210029db4c683496c6ccfce9", 
                                            "width": 640, 
                                            "height": 1137
                                        }, 
                                        {
                                            "url": "https://i.redditmedia.com/GwDNkDHfaO-SzepHuzgWLWi-4Qh3ufzt4YI3mi0Rwkw.jpg?fit=crop&amp;crop=faces%2Centropy&amp;arh=2&amp;w=960&amp;s=0875a5e382537d7cbde05fcc94808553", 
                                            "width": 960, 
                                            "height": 1706
                                        }, 
                                        {
                                            "url": "https://i.redditmedia.com/GwDNkDHfaO-SzepHuzgWLWi-4Qh3ufzt4YI3mi0Rwkw.jpg?fit=crop&amp;crop=faces%2Centropy&amp;arh=2&amp;w=1080&amp;s=2d378d37aafa95cece0345d2f34d277c", 
                                            "width": 1080, 
                                            "height": 1920
                                        }
                                    ], 
                                    "variants": {}, 
                                    "id": "OKmi0DK0m404-liYEIptVcQqyIfsgFGLyncRl6ZQuoE"
                                }
                            ], 
                            "enabled": false
                        }, 
                        "thumbnail": "https://b.thumbs.redditmedia.com/HJ6mtXWJ1kC-yzGXhpWsaq6jKxkSgbdugLAxKI9eY3I.jpg", 
                        "subreddit_id": "t5_37xo2", 
                        "edited": false, 
                        "link_flair_css_class": null, 
                        "author_flair_css_class": "roastlink", 
                        "gilded": 0, 
                        "downs": 0, 
                        "brand_safe": true, 
                        "archived": true, 
                        "removal_reason": null, 
                        "post_hint": "link", 
                        "can_gild": false, 
                        "thumbnail_height": 140, 
                        "hide_score": false, 
                        "spoiler": false, 
                        "permalink": "/r/RoastMe/comments/3t90m4/give_me_your_worst/", 
                        "num_reports": null, 
                        "locked": false, 
                        "stickied": false, 
                        "created": 1447847130.0, 
                        "url": "http://imgur.com/BbGbaV8", 
                        "author_flair_text": "http://redd.it/4xgtiz", 
                        "quarantine": false, 
                        "title": "Give me your worst", 
                        "created_utc": 1447818330.0, 
                        "distinguished": null, 
                        "media": null, 
                        "upvote_ratio": 0.81, 
                        "num_comments": 18, 
                        "is_self": false, 
                        "visited": false, 
                        "subreddit_type": "public", 
                        "is_video": false, 
                        "ups": 3
                    }
                }
            ], 
            "after": null, 
            "before": null
        }
    }, 
    {
        "kind": "Listing", 
        "data": {
            "modhash": "", 
            "children": [
                {
                    "kind": "t1", 
                    "data": {
                        "subreddit_id": "t5_37xo2", 
                        "banned_by": null, 
                        "removal_reason": null, 
                        "link_id": "t3_3t90m4", 
                        "likes": null, 
                        "replies": {
                            "kind": "Listing", 
                            "data": {
                                "modhash": "", 
                                "children": [
                                    {
                                        "kind": "t1", 
                                        "data": {
                                            "subreddit_id": "t5_37xo2", 
                                            "banned_by": null, 
                                            "removal_reason": null, 
                                            "link_id": "t3_3t90m4", 
                                            "likes": null, 
                                            "replies": "", 
                                            "user_reports": [], 
                                            "saved": false, 
                                            "id": "cx4aa98", 
                                            "gilded": 0, 
                                            "archived": true, 
                                            "score": 1, 
                                            "report_reasons": null, 
                                            "author": "Weep2D2", 
                                            "parent_id": "t1_cx45v1y", 
                                            "subreddit_name_prefixed": "r/RoastMe", 
                                            "approved_by": null, 
                                            "controversiality": 0, 
                                            "body": "She looks like a slightly melted porcelain doll.", 
                                            "edited": false, 
                                            "author_flair_css_class": null, 
                                            "downs": 0, 
                                            "body_html": "&lt;div class=\"md\"&gt;&lt;p&gt;She looks like a slightly melted porcelain doll.&lt;/p&gt;\n&lt;/div&gt;", 
                                            "can_gild": true, 
                                            "subreddit": "RoastMe", 
                                            "name": "t1_cx4aa98", 
                                            "score_hidden": false, 
                                            "num_reports": null, 
                                            "stickied": false, 
                                            "created": 1447858118.0, 
                                            "author_flair_text": null, 
                                            "created_utc": 1447829318.0, 
                                            "distinguished": null, 
                                            "depth": 1, 
                                            "mod_reports": [], 
                                            "subreddit_type": "public", 
                                            "ups": 1
                                        }
                                    }
                                ], 
                                "after": null, 
                                "before": null
                            }
                        }, 
                        "user_reports": [], 
                        "saved": false, 
                        "id": "cx45v1y", 
                        "gilded": 0, 
                        "archived": true, 
                        "score": 7, 
                        "report_reasons": null, 
                        "author": "[deleted]", 
                        "parent_id": "t3_3t90m4", 
                        "subreddit_name_prefixed": "r/RoastMe", 
                        "approved_by": null, 
                        "controversiality": 0, 
                        "body": "[deleted]", 
                        "edited": false, 
                        "author_flair_css_class": null, 
                        "downs": 0, 
                        "body_html": "&lt;div class=\"md\"&gt;&lt;p&gt;[deleted]&lt;/p&gt;\n&lt;/div&gt;", 
                        "can_gild": true, 
                        "subreddit": "RoastMe", 
                        "name": "t1_cx45v1y", 
                        "score_hidden": false, 
                        "num_reports": null, 
                        "stickied": false, 
                        "created": 1447847961.0, 
                        "author_flair_text": null, 
                        "created_utc": 1447819161.0, 
                        "distinguished": null, 
                        "depth": 0, 
                        "mod_reports": [], 
                        "subreddit_type": "public", 
                        "ups": 7
                    }
                }, 
                {
                    "kind": "t1", 
                    "data": {
                        "subreddit_id": "t5_37xo2", 
                        "banned_by": null, 
                        "removal_reason": null, 
                        "link_id": "t3_3t90m4", 
                        "likes": null, 
                        "replies": "", 
                        "user_reports": [], 
                        "saved": false, 
                        "id": "cx45wfj", 
                        "gilded": 0, 
                        "archived": true, 
                        "score": 3, 
                        "report_reasons": null, 
                        "author": "monstere316", 
                        "parent_id": "t3_3t90m4", 
                        "subreddit_name_prefixed": "r/RoastMe", 
                        "approved_by": null, 
                        "controversiality": 0, 
                        "body": "What are you gonna do when those cocoons hatch", 
                        "edited": false, 
                        "author_flair_css_class": null, 
                        "downs": 0, 
                        "body_html": "&lt;div class=\"md\"&gt;&lt;p&gt;What are you gonna do when those cocoons hatch&lt;/p&gt;\n&lt;/div&gt;", 
                        "can_gild": true, 
                        "subreddit": "RoastMe", 
                        "name": "t1_cx45wfj", 
                        "score_hidden": false, 
                        "num_reports": null, 
                        "stickied": false, 
                        "created": 1447848036.0, 
                        "author_flair_text": null, 
                        "created_utc": 1447819236.0, 
                        "distinguished": null, 
                        "depth": 0, 
                        "mod_reports": [], 
                        "subreddit_type": "public", 
                        "ups": 3
                    }
                }, 
                {
                    "kind": "t1", 
                    "data": {
                        "subreddit_id": "t5_37xo2", 
                        "banned_by": null, 
                        "removal_reason": null, 
                        "link_id": "t3_3t90m4", 
                        "likes": null, 
                        "replies": "", 
                        "user_reports": [], 
                        "saved": false, 
                        "id": "cx46b76", 
                        "gilded": 0, 
                        "archived": true, 
                        "score": 4, 
                        "report_reasons": null, 
                        "author": "Bothium", 
                        "parent_id": "t3_3t90m4", 
                        "subreddit_name_prefixed": "r/RoastMe", 
                        "approved_by": null, 
                        "controversiality": 0, 
                        "body": "You look like a preset of Joan Rivers.", 
                        "edited": false, 
                        "author_flair_css_class": "roastlink", 
                        "downs": 0, 
                        "body_html": "&lt;div class=\"md\"&gt;&lt;p&gt;You look like a preset of Joan Rivers.&lt;/p&gt;\n&lt;/div&gt;", 
                        "can_gild": true, 
                        "subreddit": "RoastMe", 
                        "name": "t1_cx46b76", 
                        "score_hidden": false, 
                        "num_reports": null, 
                        "stickied": false, 
                        "created": 1447848820.0, 
                        "author_flair_text": "http://redd.it/4pzsba", 
                        "created_utc": 1447820020.0, 
                        "distinguished": null, 
                        "depth": 0, 
                        "mod_reports": [], 
                        "subreddit_type": "public", 
                        "ups": 4
                    }
                }, 
                {
                    "kind": "t1", 
                    "data": {
                        "subreddit_id": "t5_37xo2", 
                        "banned_by": null, 
                        "removal_reason": null, 
                        "link_id": "t3_3t90m4", 
                        "likes": null, 
                        "replies": "", 
                        "user_reports": [], 
                        "saved": false, 
                        "id": "cx46gmb", 
                        "gilded": 0, 
                        "archived": true, 
                        "score": 4, 
                        "report_reasons": null, 
                        "author": "Motorhed00", 
                        "parent_id": "t3_3t90m4", 
                        "subreddit_name_prefixed": "r/RoastMe", 
                        "approved_by": null, 
                        "controversiality": 0, 
                        "body": "You're cute! No wonder why your moms boyfriend used to make you fuck him", 
                        "edited": false, 
                        "author_flair_css_class": null, 
                        "downs": 0, 
                        "body_html": "&lt;div class=\"md\"&gt;&lt;p&gt;You&amp;#39;re cute! No wonder why your moms boyfriend used to make you fuck him&lt;/p&gt;\n&lt;/div&gt;", 
                        "can_gild": true, 
                        "subreddit": "RoastMe", 
                        "name": "t1_cx46gmb", 
                        "score_hidden": false, 
                        "num_reports": null, 
                        "stickied": false, 
                        "created": 1447849117.0, 
                        "author_flair_text": null, 
                        "created_utc": 1447820317.0, 
                        "distinguished": null, 
                        "depth": 0, 
                        "mod_reports": [], 
                        "subreddit_type": "public", 
                        "ups": 4
                    }
                }, 
                {
                    "kind": "t1", 
                    "data": {
                        "subreddit_id": "t5_37xo2", 
                        "banned_by": null, 
                        "removal_reason": null, 
                        "link_id": "t3_3t90m4", 
                        "likes": null, 
                        "replies": "", 
                        "user_reports": [], 
                        "saved": false, 
                        "id": "cx4a2gl", 
                        "gilded": 0, 
                        "archived": true, 
                        "score": 4, 
                        "report_reasons": null, 
                        "author": "ClitoriasSecret", 
                        "parent_id": "t3_3t90m4", 
                        "subreddit_name_prefixed": "r/RoastMe", 
                        "approved_by": null, 
                        "controversiality": 0, 
                        "body": "You're going to save a lot of money on sex toys with those sausage fingers. ", 
                        "edited": false, 
                        "author_flair_css_class": null, 
                        "downs": 0, 
                        "body_html": "&lt;div class=\"md\"&gt;&lt;p&gt;You&amp;#39;re going to save a lot of money on sex toys with those sausage fingers. &lt;/p&gt;\n&lt;/div&gt;", 
                        "can_gild": true, 
                        "subreddit": "RoastMe", 
                        "name": "t1_cx4a2gl", 
                        "score_hidden": false, 
                        "num_reports": null, 
                        "stickied": false, 
                        "created": 1447857484.0, 
                        "author_flair_text": null, 
                        "created_utc": 1447828684.0, 
                        "distinguished": null, 
                        "depth": 0, 
                        "mod_reports": [], 
                        "subreddit_type": "public", 
                        "ups": 4
                    }
                }, 
                {
                    "kind": "t1", 
                    "data": {
                        "subreddit_id": "t5_37xo2", 
                        "banned_by": null, 
                        "removal_reason": null, 
                        "link_id": "t3_3t90m4", 
                        "likes": null, 
                        "replies": "", 
                        "user_reports": [], 
                        "saved": false, 
                        "id": "cx4ewmc", 
                        "gilded": 0, 
                        "archived": true, 
                        "score": 2, 
                        "report_reasons": null, 
                        "author": "Inuysha0222", 
                        "parent_id": "t3_3t90m4", 
                        "subreddit_name_prefixed": "r/RoastMe", 
                        "approved_by": null, 
                        "controversiality": 0, 
                        "body": "That face you're making looks like a mix of daddy issues and self loathing. No wonder guys only want to bang you.", 
                        "edited": false, 
                        "author_flair_css_class": null, 
                        "downs": 0, 
                        "body_html": "&lt;div class=\"md\"&gt;&lt;p&gt;That face you&amp;#39;re making looks like a mix of daddy issues and self loathing. No wonder guys only want to bang you.&lt;/p&gt;\n&lt;/div&gt;", 
                        "can_gild": true, 
                        "subreddit": "RoastMe", 
                        "name": "t1_cx4ewmc", 
                        "score_hidden": false, 
                        "num_reports": null, 
                        "stickied": false, 
                        "created": 1447876818.0, 
                        "author_flair_text": null, 
                        "created_utc": 1447848018.0, 
                        "distinguished": null, 
                        "depth": 0, 
                        "mod_reports": [], 
                        "subreddit_type": "public", 
                        "ups": 2
                    }
                }, 
                {
                    "kind": "t1", 
                    "data": {
                        "subreddit_id": "t5_37xo2", 
                        "banned_by": null, 
                        "removal_reason": null, 
                        "link_id": "t3_3t90m4", 
                        "likes": null, 
                        "replies": "", 
                        "user_reports": [], 
                        "saved": false, 
                        "id": "cx474pw", 
                        "gilded": 0, 
                        "archived": true, 
                        "score": 1, 
                        "report_reasons": null, 
                        "author": "Sormaj", 
                        "parent_id": "t3_3t90m4", 
                        "subreddit_name_prefixed": "r/RoastMe", 
                        "approved_by": null, 
                        "controversiality": 0, 
                        "body": "You have this look on your face that says \"My boyfriend left me for my sister\"", 
                        "edited": false, 
                        "author_flair_css_class": null, 
                        "downs": 0, 
                        "body_html": "&lt;div class=\"md\"&gt;&lt;p&gt;You have this look on your face that says &amp;quot;My boyfriend left me for my sister&amp;quot;&lt;/p&gt;\n&lt;/div&gt;", 
                        "can_gild": true, 
                        "subreddit": "RoastMe", 
                        "name": "t1_cx474pw", 
                        "score_hidden": false, 
                        "num_reports": null, 
                        "stickied": false, 
                        "created": 1447850452.0, 
                        "author_flair_text": null, 
                        "created_utc": 1447821652.0, 
                        "distinguished": null, 
                        "depth": 0, 
                        "mod_reports": [], 
                        "subreddit_type": "public", 
                        "ups": 1
                    }
                }, 
                {
                    "kind": "t1", 
                    "data": {
                        "subreddit_id": "t5_37xo2", 
                        "banned_by": null, 
                        "removal_reason": null, 
                        "link_id": "t3_3t90m4", 
                        "likes": null, 
                        "replies": "", 
                        "user_reports": [], 
                        "saved": false, 
                        "id": "cx47abs", 
                        "gilded": 0, 
                        "archived": true, 
                        "score": 1, 
                        "report_reasons": null, 
                        "author": "Choeseph_Hilbe", 
                        "parent_id": "t3_3t90m4", 
                        "subreddit_name_prefixed": "r/RoastMe", 
                        "approved_by": null, 
                        "controversiality": 0, 
                        "body": "Your face really does get rid of wood. Hell it did a number on the tree on your sweatshirt.", 
                        "edited": false, 
                        "author_flair_css_class": null, 
                        "downs": 0, 
                        "body_html": "&lt;div class=\"md\"&gt;&lt;p&gt;Your face really does get rid of wood. Hell it did a number on the tree on your sweatshirt.&lt;/p&gt;\n&lt;/div&gt;", 
                        "can_gild": true, 
                        "subreddit": "RoastMe", 
                        "name": "t1_cx47abs", 
                        "score_hidden": false, 
                        "num_reports": null, 
                        "stickied": false, 
                        "created": 1447850779.0, 
                        "author_flair_text": null, 
                        "created_utc": 1447821979.0, 
                        "distinguished": null, 
                        "depth": 0, 
                        "mod_reports": [], 
                        "subreddit_type": "public", 
                        "ups": 1
                    }
                }, 
                {
                    "kind": "t1", 
                    "data": {
                        "subreddit_id": "t5_37xo2", 
                        "banned_by": null, 
                        "removal_reason": null, 
                        "link_id": "t3_3t90m4", 
                        "likes": null, 
                        "replies": "", 
                        "user_reports": [], 
                        "saved": false, 
                        "id": "cx47c0o", 
                        "gilded": 0, 
                        "archived": true, 
                        "score": 1, 
                        "report_reasons": null, 
                        "author": "thedeuce75", 
                        "parent_id": "t3_3t90m4", 
                        "subreddit_name_prefixed": "r/RoastMe", 
                        "approved_by": null, 
                        "controversiality": 0, 
                        "body": "I bet your eyebrows smell just like a sharpie.", 
                        "edited": false, 
                        "author_flair_css_class": null, 
                        "downs": 0, 
                        "body_html": "&lt;div class=\"md\"&gt;&lt;p&gt;I bet your eyebrows smell just like a sharpie.&lt;/p&gt;\n&lt;/div&gt;", 
                        "can_gild": true, 
                        "subreddit": "RoastMe", 
                        "name": "t1_cx47c0o", 
                        "score_hidden": false, 
                        "num_reports": null, 
                        "stickied": false, 
                        "created": 1447850876.0, 
                        "author_flair_text": null, 
                        "created_utc": 1447822076.0, 
                        "distinguished": null, 
                        "depth": 0, 
                        "mod_reports": [], 
                        "subreddit_type": "public", 
                        "ups": 1
                    }
                }, 
                {
                    "kind": "t1", 
                    "data": {
                        "subreddit_id": "t5_37xo2", 
                        "banned_by": null, 
                        "removal_reason": null, 
                        "link_id": "t3_3t90m4", 
                        "likes": null, 
                        "replies": "", 
                        "user_reports": [], 
                        "saved": false, 
                        "id": "cx47x2o", 
                        "gilded": 0, 
                        "archived": true, 
                        "score": 1, 
                        "report_reasons": null, 
                        "author": "DharmaSmokeMonster", 
                        "parent_id": "t3_3t90m4", 
                        "subreddit_name_prefixed": "r/RoastMe", 
                        "approved_by": null, 
                        "controversiality": 0, 
                        "body": "What's the hospital receipt for, sex change surgery?", 
                        "edited": false, 
                        "author_flair_css_class": null, 
                        "downs": 0, 
                        "body_html": "&lt;div class=\"md\"&gt;&lt;p&gt;What&amp;#39;s the hospital receipt for, sex change surgery?&lt;/p&gt;\n&lt;/div&gt;", 
                        "can_gild": true, 
                        "subreddit": "RoastMe", 
                        "name": "t1_cx47x2o", 
                        "score_hidden": false, 
                        "num_reports": null, 
                        "stickied": false, 
                        "created": 1447852142.0, 
                        "author_flair_text": null, 
                        "created_utc": 1447823342.0, 
                        "distinguished": null, 
                        "depth": 0, 
                        "mod_reports": [], 
                        "subreddit_type": "public", 
                        "ups": 1
                    }
                }, 
                {
                    "kind": "t1", 
                    "data": {
                        "subreddit_id": "t5_37xo2", 
                        "banned_by": null, 
                        "removal_reason": null, 
                        "link_id": "t3_3t90m4", 
                        "likes": null, 
                        "replies": "", 
                        "user_reports": [], 
                        "saved": false, 
                        "id": "cx481ue", 
                        "gilded": 0, 
                        "archived": true, 
                        "score": 1, 
                        "report_reasons": null, 
                        "author": "omyhomyboy", 
                        "parent_id": "t3_3t90m4", 
                        "subreddit_name_prefixed": "r/RoastMe", 
                        "approved_by": null, 
                        "controversiality": 0, 
                        "body": "[I found where you got your eyebrow game](http://i.imgur.com/66bIQV0.png)", 
                        "edited": false, 
                        "author_flair_css_class": null, 
                        "downs": 0, 
                        "body_html": "&lt;div class=\"md\"&gt;&lt;p&gt;&lt;a href=\"http://i.imgur.com/66bIQV0.png\"&gt;I found where you got your eyebrow game&lt;/a&gt;&lt;/p&gt;\n&lt;/div&gt;", 
                        "can_gild": true, 
                        "subreddit": "RoastMe", 
                        "name": "t1_cx481ue", 
                        "score_hidden": false, 
                        "num_reports": null, 
                        "stickied": false, 
                        "created": 1447852440.0, 
                        "author_flair_text": null, 
                        "created_utc": 1447823640.0, 
                        "distinguished": null, 
                        "depth": 0, 
                        "mod_reports": [], 
                        "subreddit_type": "public", 
                        "ups": 1
                    }
                }, 
                {
                    "kind": "t1", 
                    "data": {
                        "subreddit_id": "t5_37xo2", 
                        "banned_by": null, 
                        "removal_reason": null, 
                        "link_id": "t3_3t90m4", 
                        "likes": null, 
                        "replies": "", 
                        "user_reports": [], 
                        "saved": false, 
                        "id": "cx48b3u", 
                        "gilded": 0, 
                        "archived": true, 
                        "score": 1, 
                        "report_reasons": null, 
                        "author": "Tempted_Muffin", 
                        "parent_id": "t3_3t90m4", 
                        "subreddit_name_prefixed": "r/RoastMe", 
                        "approved_by": null, 
                        "controversiality": 0, 
                        "body": "Cause you've already given us yours?", 
                        "edited": false, 
                        "author_flair_css_class": null, 
                        "downs": 0, 
                        "body_html": "&lt;div class=\"md\"&gt;&lt;p&gt;Cause you&amp;#39;ve already given us yours?&lt;/p&gt;\n&lt;/div&gt;", 
                        "can_gild": true, 
                        "subreddit": "RoastMe", 
                        "name": "t1_cx48b3u", 
                        "score_hidden": false, 
                        "num_reports": null, 
                        "stickied": false, 
                        "created": 1447853029.0, 
                        "author_flair_text": null, 
                        "created_utc": 1447824229.0, 
                        "distinguished": null, 
                        "depth": 0, 
                        "mod_reports": [], 
                        "subreddit_type": "public", 
                        "ups": 1
                    }
                }, 
                {
                    "kind": "t1", 
                    "data": {
                        "subreddit_id": "t5_37xo2", 
                        "banned_by": null, 
                        "removal_reason": null, 
                        "link_id": "t3_3t90m4", 
                        "likes": null, 
                        "replies": "", 
                        "user_reports": [], 
                        "saved": false, 
                        "id": "cx4a3kc", 
                        "gilded": 0, 
                        "archived": true, 
                        "score": 1, 
                        "report_reasons": null, 
                        "author": "RustyCock", 
                        "parent_id": "t3_3t90m4", 
                        "subreddit_name_prefixed": "r/RoastMe", 
                        "approved_by": null, 
                        "controversiality": 0, 
                        "body": "Wanna do an /r/gwcouples post together?", 
                        "edited": false, 
                        "author_flair_css_class": null, 
                        "downs": 0, 
                        "body_html": "&lt;div class=\"md\"&gt;&lt;p&gt;Wanna do an &lt;a href=\"/r/gwcouples\"&gt;/r/gwcouples&lt;/a&gt; post together?&lt;/p&gt;\n&lt;/div&gt;", 
                        "can_gild": true, 
                        "subreddit": "RoastMe", 
                        "name": "t1_cx4a3kc", 
                        "score_hidden": false, 
                        "num_reports": null, 
                        "stickied": false, 
                        "created": 1447857577.0, 
                        "author_flair_text": null, 
                        "created_utc": 1447828777.0, 
                        "distinguished": null, 
                        "depth": 0, 
                        "mod_reports": [], 
                        "subreddit_type": "public", 
                        "ups": 1
                    }
                }, 
                {
                    "kind": "t1", 
                    "data": {
                        "subreddit_id": "t5_37xo2", 
                        "banned_by": null, 
                        "removal_reason": null, 
                        "link_id": "t3_3t90m4", 
                        "likes": null, 
                        "replies": "", 
                        "user_reports": [], 
                        "saved": false, 
                        "id": "cx4ahv4", 
                        "gilded": 0, 
                        "archived": true, 
                        "score": 1, 
                        "report_reasons": null, 
                        "author": "centwobklyn", 
                        "parent_id": "t3_3t90m4", 
                        "subreddit_name_prefixed": "r/RoastMe", 
                        "approved_by": null, 
                        "controversiality": 0, 
                        "body": "Which one of you guys photo shopped caterpillars onto this raccoon's face?", 
                        "edited": false, 
                        "author_flair_css_class": null, 
                        "downs": 0, 
                        "body_html": "&lt;div class=\"md\"&gt;&lt;p&gt;Which one of you guys photo shopped caterpillars onto this raccoon&amp;#39;s face?&lt;/p&gt;\n&lt;/div&gt;", 
                        "can_gild": true, 
                        "subreddit": "RoastMe", 
                        "name": "t1_cx4ahv4", 
                        "score_hidden": false, 
                        "num_reports": null, 
                        "stickied": false, 
                        "created": 1447858772.0, 
                        "author_flair_text": null, 
                        "created_utc": 1447829972.0, 
                        "distinguished": null, 
                        "depth": 0, 
                        "mod_reports": [], 
                        "subreddit_type": "public", 
                        "ups": 1
                    }
                }, 
                {
                    "kind": "t1", 
                    "data": {
                        "subreddit_id": "t5_37xo2", 
                        "banned_by": null, 
                        "removal_reason": null, 
                        "link_id": "t3_3t90m4", 
                        "likes": null, 
                        "replies": "", 
                        "user_reports": [], 
                        "saved": false, 
                        "id": "cx4ap2o", 
                        "gilded": 0, 
                        "archived": true, 
                        "score": 1, 
                        "report_reasons": null, 
                        "author": "shenzi_mtoto", 
                        "parent_id": "t3_3t90m4", 
                        "subreddit_name_prefixed": "r/RoastMe", 
                        "approved_by": null, 
                        "controversiality": 0, 
                        "body": "You look glued together.", 
                        "edited": false, 
                        "author_flair_css_class": null, 
                        "downs": 0, 
                        "body_html": "&lt;div class=\"md\"&gt;&lt;p&gt;You look glued together.&lt;/p&gt;\n&lt;/div&gt;", 
                        "can_gild": true, 
                        "subreddit": "RoastMe", 
                        "name": "t1_cx4ap2o", 
                        "score_hidden": false, 
                        "num_reports": null, 
                        "stickied": false, 
                        "created": 1447859416.0, 
                        "author_flair_text": null, 
                        "created_utc": 1447830616.0, 
                        "distinguished": null, 
                        "depth": 0, 
                        "mod_reports": [], 
                        "subreddit_type": "public", 
                        "ups": 1
                    }
                }, 
                {
                    "kind": "t1", 
                    "data": {
                        "subreddit_id": "t5_37xo2", 
                        "banned_by": null, 
                        "removal_reason": null, 
                        "link_id": "t3_3t90m4", 
                        "likes": null, 
                        "replies": "", 
                        "user_reports": [], 
                        "saved": false, 
                        "id": "cx4aqpr", 
                        "gilded": 0, 
                        "archived": true, 
                        "score": 1, 
                        "report_reasons": null, 
                        "author": "Proclaim_the_Name", 
                        "parent_id": "t3_3t90m4", 
                        "subreddit_name_prefixed": "r/RoastMe", 
                        "approved_by": null, 
                        "controversiality": 0, 
                        "body": "Did you just print out apostrophes and tape them to your forehead?", 
                        "edited": false, 
                        "author_flair_css_class": null, 
                        "downs": 0, 
                        "body_html": "&lt;div class=\"md\"&gt;&lt;p&gt;Did you just print out apostrophes and tape them to your forehead?&lt;/p&gt;\n&lt;/div&gt;", 
                        "can_gild": true, 
                        "subreddit": "RoastMe", 
                        "name": "t1_cx4aqpr", 
                        "score_hidden": false, 
                        "num_reports": null, 
                        "stickied": false, 
                        "created": 1447859567.0, 
                        "author_flair_text": null, 
                        "created_utc": 1447830767.0, 
                        "distinguished": null, 
                        "depth": 0, 
                        "mod_reports": [], 
                        "subreddit_type": "public", 
                        "ups": 1
                    }
                }, 
                {
                    "kind": "t1", 
                    "data": {
                        "subreddit_id": "t5_37xo2", 
                        "banned_by": null, 
                        "removal_reason": null, 
                        "link_id": "t3_3t90m4", 
                        "likes": null, 
                        "replies": "", 
                        "user_reports": [], 
                        "saved": false, 
                        "id": "cx4c1f4", 
                        "gilded": 0, 
                        "archived": true, 
                        "score": 1, 
                        "report_reasons": null, 
                        "author": "southsamurai", 
                        "parent_id": "t3_3t90m4", 
                        "subreddit_name_prefixed": "r/RoastMe", 
                        "approved_by": null, 
                        "controversiality": 0, 
                        "body": "It's a princess! Admittedly, it's a wax statue of snow white that got melted in the face, but still", 
                        "edited": false, 
                        "author_flair_css_class": null, 
                        "downs": 0, 
                        "body_html": "&lt;div class=\"md\"&gt;&lt;p&gt;It&amp;#39;s a princess! Admittedly, it&amp;#39;s a wax statue of snow white that got melted in the face, but still&lt;/p&gt;\n&lt;/div&gt;", 
                        "can_gild": true, 
                        "subreddit": "RoastMe", 
                        "name": "t1_cx4c1f4", 
                        "score_hidden": false, 
                        "num_reports": null, 
                        "stickied": false, 
                        "created": 1447864316.0, 
                        "author_flair_text": null, 
                        "created_utc": 1447835516.0, 
                        "distinguished": null, 
                        "depth": 0, 
                        "mod_reports": [], 
                        "subreddit_type": "public", 
                        "ups": 1
                    }
                }, 
                {
                    "kind": "t1", 
                    "data": {
                        "subreddit_id": "t5_37xo2", 
                        "banned_by": null, 
                        "removal_reason": null, 
                        "link_id": "t3_3t90m4", 
                        "likes": null, 
                        "replies": "", 
                        "user_reports": [], 
                        "saved": false, 
                        "id": "cx4m26j", 
                        "gilded": 0, 
                        "archived": true, 
                        "score": 1, 
                        "report_reasons": null, 
                        "author": "ALtheMangl3r", 
                        "parent_id": "t3_3t90m4", 
                        "subreddit_name_prefixed": "r/RoastMe", 
                        "approved_by": null, 
                        "controversiality": 0, 
                        "body": "Your eyebrows look like they're mad at your face and are just walking away.", 
                        "edited": false, 
                        "author_flair_css_class": null, 
                        "downs": 0, 
                        "body_html": "&lt;div class=\"md\"&gt;&lt;p&gt;Your eyebrows look like they&amp;#39;re mad at your face and are just walking away.&lt;/p&gt;\n&lt;/div&gt;", 
                        "can_gild": true, 
                        "subreddit": "RoastMe", 
                        "name": "t1_cx4m26j", 
                        "score_hidden": false, 
                        "num_reports": null, 
                        "stickied": false, 
                        "created": 1447892240.0, 
                        "author_flair_text": null, 
                        "created_utc": 1447863440.0, 
                        "distinguished": null, 
                        "depth": 0, 
                        "mod_reports": [], 
                        "subreddit_type": "public", 
                        "ups": 1
                    }
                }
            ], 
            "after": null, 
            "before": null
        }
    }
]